gauss6/__init__.py
gauss6/central_differences.py
gauss6/gauss6.py
gauss6/gmres.py
gauss6-0.1.1.dist-info/licenses/LICENSE
gauss6-0.1.1.dist-info/METADATA
gauss6-0.1.1.dist-info/WHEEL
gauss6-0.1.1.dist-info/top_level.txt
gauss6-0.1.1.dist-info/RECORD
