Metadata-Version: 2.4
Name: gauss6
Version: 0.1.1
Summary: Gauss-Legendre 6th-order implicit integrator and finite-difference helpers built on JAX.
Author: Eirik
License: MIT License
Classifier: Development Status :: 3 - Alpha
Classifier: Intended Audience :: Science/Research
Classifier: License :: OSI Approved :: MIT License
Classifier: Programming Language :: Python
Classifier: Programming Language :: Python :: 3
Classifier: Programming Language :: Python :: 3.9
Classifier: Programming Language :: Python :: 3.10
Classifier: Programming Language :: Python :: 3.11
Classifier: Programming Language :: Python :: 3.12
Classifier: Topic :: Scientific/Engineering
Classifier: Topic :: Scientific/Engineering :: Mathematics
Requires-Python: >=3.9
License-File: LICENSE
Requires-Dist: jax>=0.4.20
Requires-Dist: jax-tqdm>=0.1.0
Requires-Dist: sparsejac>=0.2.0
Provides-Extra: dev
Requires-Dist: build>=1.0.0; extra == "dev"
Dynamic: license-file
